cj7/__init__.py
cj7/cj7.py
cj7-0.0.1.dist-info/LICENSE
cj7-0.0.1.dist-info/METADATA
cj7-0.0.1.dist-info/WHEEL
cj7-0.0.1.dist-info/top_level.txt
cj7-0.0.1.dist-info/RECORD
