Metadata-Version: 2.1
Name: cj7
Version: 0.0.1
Summary: A simple way for TCP and UDP communication.
Home-page: https://github.com/jack-debug/cj7
Author: jack-debug
Author-email: author@example.com
License: UNKNOWN
Project-URL: Bug Tracker, https://github.com/jack-debug/cj7/issues
Platform: UNKNOWN
Classifier: Programming Language :: Python :: 3
Classifier: License :: OSI Approved :: MIT License
Classifier: Operating System :: OS Independent
Requires-Python: >=3.6
License-File: LICENSE
